revisit/__init__.py
revisit/cli.py
revisit/commands/__init__.py
revisit/commands/add_command.py
revisit/commands/check_command.py
revisit/commands/delete_command.py
revisit/commands/export_command.py
revisit/commands/import_command.py
revisit/commands/open_command.py
revisit/commands/print_command.py
revisit/commands/server_command.py
revisit/commands/update_command.py
revisit/commands/version_command.py
revisit/core/__init__.py
revisit/core/utils.py
revisit/db/__init__.py
revisit/db/sqlite/__init__.py
revisit/db/sqlite/manager.py
revisit/db/sqlite/repository.py
revisit/db/sqlite/migrations/001_create_bookmarks_table.sql
revisit/domain/__init__.py
revisit/domain/bookmark.py
revisit_bookmarks-0.1.1.dist-info/METADATA
revisit_bookmarks-0.1.1.dist-info/WHEEL
revisit_bookmarks-0.1.1.dist-info/entry_points.txt
revisit_bookmarks-0.1.1.dist-info/top_level.txt
revisit_bookmarks-0.1.1.dist-info/RECORD
