Metadata-Version: 2.4
Name: revisit-bookmarks
Version: 0.1.1
Summary: Simple bookmark manager with custom webview
Requires-Python: >=3.12
Requires-Dist: click>=8.3.1
Requires-Dist: flask>=3.1.2
Requires-Dist: requests>=2.32.5
